laue_crystallography/__init__.py
laue_crystallography/_version.py
laue_crystallography/microfluidics.py
laue_crystallography/tests/__init__.py
laue_crystallography/tests/conftest.py
laue_crystallography/tests/test_examples.py
laue_crystallography-0.0.1.dist-info/AUTHORS.rst
laue_crystallography-0.0.1.dist-info/LICENSE
laue_crystallography-0.0.1.dist-info/METADATA
laue_crystallography-0.0.1.dist-info/WHEEL
laue_crystallography-0.0.1.dist-info/entry_points.txt
laue_crystallography-0.0.1.dist-info/top_level.txt
laue_crystallography-0.0.1.dist-info/RECORD
