Metadata-Version: 2.1
Name: laue-crystallography
Version: 0.0.1
Summary: Laue crystallography
Home-page: https://github.com/vstadnytskyi/laue-crystallography
Author: Valentyn Stadnytskyi
Author-email: v.stadnytskyi@gmail.com
License: BSD (3-clause)
Platform: UNKNOWN
Classifier: Development Status :: 2 - Pre-Alpha
Classifier: Natural Language :: English
Classifier: Programming Language :: Python :: 3
Requires-Python: >=3.6
